pycolombianizer/__init__.py
pycolombianizer/cli.py
pycolombianizer/pycolombianizer.py
pycolombianizer-0.2.0.dist-info/DESCRIPTION.rst
pycolombianizer-0.2.0.dist-info/METADATA
pycolombianizer-0.2.0.dist-info/RECORD
pycolombianizer-0.2.0.dist-info/WHEEL
pycolombianizer-0.2.0.dist-info/entry_points.txt
pycolombianizer-0.2.0.dist-info/metadata.json
pycolombianizer-0.2.0.dist-info/top_level.txt
