Metadata-Version: 2.0
Name: pycolombianizer
Version: 0.2.0
Summary: Colombianize a string
Home-page: https://github.com/jcrodriguezu/pycolombianizer
Author: Juan C. Rodriguez
Author-email: jcrodriguezu@gmail.com
License: GNU General Public License v3
Keywords: pycolombianizer
Platform: UNKNOWN
Classifier: Development Status :: 2 - Pre-Alpha
Classifier: Intended Audience :: Developers
Classifier: License :: OSI Approved :: GNU General Public License v3 (GPLv3)
Classifier: Natural Language :: English
Classifier: Programming Language :: Python :: 2
Classifier: Programming Language :: Python :: 2.7
Classifier: Programming Language :: Python :: 3
Classifier: Programming Language :: Python :: 3.4
Classifier: Programming Language :: Python :: 3.5
Classifier: Programming Language :: Python :: 3.6
Requires-Dist: Click (>=6.0)
